gatria/__init__.py
gatria/adapters.py
gatria/attendance.py
gatria/config.py
gatria/interfaces.py
gatria/leave_management.py
gatria/performance.py
gatria/storage.py
gatria/utils.py
gatria/adapters/__init__.py
gatria/adapters/base.py
gatria/adapters/module_adapters.py
gatria/web/__init__.py
gatria/web/adapters.py
gatria/web/middleware.py
gatria/web/responses.py
gatria-0.1.1.dist-info/LICENSE
gatria-0.1.1.dist-info/METADATA
gatria-0.1.1.dist-info/WHEEL
gatria-0.1.1.dist-info/top_level.txt
gatria-0.1.1.dist-info/RECORD
