Metadata-Version: 2.1
Name: gatria
Version: 0.1.1
Summary: A comprehensive employee management system with multiple framework adapters
Home-page: https://github.com/Canopus-Development/Gatria
Author: Pradyumn Tandon
Author-email: pradyumn.tandon@hotmail.com
Classifier: Development Status :: 3 - Alpha
Classifier: Intended Audience :: Developers
Classifier: Programming Language :: Python :: 3
Classifier: Programming Language :: Python :: 3.8
Classifier: Programming Language :: Python :: 3.9
Classifier: Programming Language :: Python :: 3.10
Classifier: Programming Language :: Python :: 3.11
Classifier: Programming Language :: Python :: 3.12
Classifier: License :: OSI Approved :: MIT License
Classifier: Operating System :: OS Independent
Requires-Python: >=3.8
License-File: LICENSE
Requires-Dist: flask>=2.0.0
Requires-Dist: django>=4.0.0
Requires-Dist: sqlalchemy>=1.4.0
Requires-Dist: pymongo>=4.0.0
Requires-Dist: aiohttp>=3.8.0
Provides-Extra: web
Requires-Dist: flask>=2.0.0; extra == "web"
Requires-Dist: django>=4.0.0; extra == "web"
Requires-Dist: fastapi>=0.68.0; extra == "web"
Requires-Dist: uvicorn>=0.15.0; extra == "web"
Requires-Dist: werkzeug>=2.0.0; extra == "web"
Requires-Dist: django-rest-framework>=3.12.0; extra == "web"
Provides-Extra: database
Requires-Dist: sqlalchemy>=1.4.0; extra == "database"
Requires-Dist: pymongo>=4.0.0; extra == "database"
Requires-Dist: redis>=4.0.0; extra == "database"
Requires-Dist: psycopg2-binary>=2.9.0; extra == "database"
Provides-Extra: async
Requires-Dist: aiohttp>=3.8.0; extra == "async"
Requires-Dist: asyncio>=3.4.3; extra == "async"
Requires-Dist: websockets>=10.0; extra == "async"
Provides-Extra: ml
Requires-Dist: scikit-learn>=1.0.0; extra == "ml"
Requires-Dist: tensorflow>=2.0.0; extra == "ml"
Requires-Dist: torch>=1.9.0; extra == "ml"
Requires-Dist: numpy>=1.20.0; extra == "ml"
Requires-Dist: pandas>=1.3.0; extra == "ml"
Provides-Extra: dev
Requires-Dist: pytest>=6.0.0; extra == "dev"
Requires-Dist: black>=21.0.0; extra == "dev"
Requires-Dist: isort>=5.0.0; extra == "dev"
Requires-Dist: mypy>=0.900; extra == "dev"
Requires-Dist: flake8>=3.9.0; extra == "dev"
Requires-Dist: pytest-cov>=2.12.0; extra == "dev"
Requires-Dist: tox>=3.24.0; extra == "dev"
